mkdocs_custommill/404.html
mkdocs_custommill/__init__.py
mkdocs_custommill/article-nav.html
mkdocs_custommill/base.html
mkdocs_custommill/index.html
mkdocs_custommill/main.html
mkdocs_custommill/mkdocs_theme.yml
mkdocs_custommill/nav-info.html
mkdocs_custommill/nav-item.html
mkdocs_custommill/nav-links.html
mkdocs_custommill/nav-pane.html
mkdocs_custommill/page-nav-urls.html
mkdocs_custommill/repo-icon.html
mkdocs_custommill/search.html
mkdocs_custommill/topbar.html
mkdocs_custommill/bootstrap/dist/css/bootstrap.min.css
mkdocs_custommill/bootstrap/dist/js/bootstrap.min.js
mkdocs_custommill/css/base.css
mkdocs_custommill/css/bootstrap-4.4.1.css
mkdocs_custommill/css/bootstrap-4.4.1.min.css
mkdocs_custommill/css/bootstrap-5.0.0-beta.1.min.css
mkdocs_custommill/css/bootstrap-5.0.1.min.css
mkdocs_custommill/css/font-awesome-4.7.0.css
mkdocs_custommill/css/font-awesome-4.7.0.min.css
mkdocs_custommill/css/font-awesome-5.12.2-all.min.css
mkdocs_custommill/css/highlight-github.css
mkdocs_custommill/fonts/fontawesome-webfont.eot
mkdocs_custommill/fonts/fontawesome-webfont.svg
mkdocs_custommill/fonts/fontawesome-webfont.ttf
mkdocs_custommill/fonts/fontawesome-webfont.woff
mkdocs_custommill/fonts/fontawesome-webfont.woff2
mkdocs_custommill/fonts/glyphicons-halflings-regular.eot
mkdocs_custommill/fonts/glyphicons-halflings-regular.svg
mkdocs_custommill/fonts/glyphicons-halflings-regular.ttf
mkdocs_custommill/fonts/glyphicons-halflings-regular.woff
mkdocs_custommill/fonts/glyphicons-halflings-regular.woff2
mkdocs_custommill/img/favicon.ico
mkdocs_custommill/js/base.js
mkdocs_custommill/js/bootstrap-4.4.1.js
mkdocs_custommill/js/bootstrap-4.4.1.min.js
mkdocs_custommill/js/bootstrap-5.0.0-beta.1.min.js
mkdocs_custommill/js/bootstrap-5.0.1.min.js
mkdocs_custommill/js/elasticlunr.js
mkdocs_custommill/js/elasticlunr.min.js
mkdocs_custommill/js/highlight.pack.js
mkdocs_custommill/js/jquery-3.2.1.js
mkdocs_custommill/js/jquery-3.2.1.min.js
mkdocs_custommill/js/jquery-3.5.1.min.js
mkdocs_custommill-1.3.0.dist-info/LICENSE
mkdocs_custommill-1.3.0.dist-info/METADATA
mkdocs_custommill-1.3.0.dist-info/WHEEL
mkdocs_custommill-1.3.0.dist-info/entry_points.txt
mkdocs_custommill-1.3.0.dist-info/top_level.txt
mkdocs_custommill-1.3.0.dist-info/RECORD
