Metadata-Version: 2.1
Name: mkdocs-custommill
Version: 1.3.0
Summary: Improved and extended version of the Windmill theme
Home-page: https://github.com/Siphalor/mkdocs-custommill
Author: Siphalor
Author-email: dev@siphalor.de
License: MIT
Platform: UNKNOWN
Classifier: License :: OSI Approved :: MIT License
Classifier: Topic :: Documentation
Classifier: Topic :: Text Processing
Requires-Dist: mkdocs
